Metadata-Version: 2.1
Name: docker-banner-gen
Version: 0.0.8
Summary: Command-line tool for generating bash.bashrc templates for docker with a custom banner.
Home-page: https://github.com/waikato-datamining/docker-banner-gen
Author: Peter Reutemann
Author-email: fracpete@waikato.ac.nz
License: Apache 2.0
Classifier: Development Status :: 4 - Beta
Classifier: License :: OSI Approved :: Apache Software License
Classifier: Topic :: System :: Shells
Classifier: Programming Language :: Python :: 3
License-File: LICENSE
Requires-Dist: pyfiglet
